zstest1/__init__.py
zstest1-0.0.1.dist-info/METADATA
zstest1-0.0.1.dist-info/WHEEL
zstest1-0.0.1.dist-info/licenses/LICENSE
zstest1-0.0.1.dist-info/RECORD
