Metadata-Version: 2.4
Name: zstest1
Version: 0.0.1
Summary: Defensive package registration to prevent supply chain attacks
Project-URL: Homepage, https://github.com/security-team/defensive-packages
Author-email: Security Team <security@company.com>
License: MIT
License-File: LICENSE
Classifier: Development Status :: 1 - Planning
Classifier: Intended Audience :: Developers
Classifier: License :: OSI Approved :: MIT License
Classifier: Programming Language :: Python :: 3
Classifier: Topic :: Security
Requires-Python: >=3.6
